easytrajh5/__init__.py
easytrajh5/binary.py
easytrajh5/cli.py
easytrajh5/fs.py
easytrajh5/h5.py
easytrajh5/manager.py
easytrajh5/pdb.py
easytrajh5/quantity.py
easytrajh5/select.py
easytrajh5/show.py
easytrajh5/struct.py
easytrajh5/traj.py
easytrajh5/data/select.yaml
easytrajh5-0.2.17.dist-info/METADATA
easytrajh5-0.2.17.dist-info/WHEEL
easytrajh5-0.2.17.dist-info/entry_points.txt
easytrajh5-0.2.17.dist-info/licenses/LICENSE
easytrajh5-0.2.17.dist-info/RECORD
