Metadata-Version: 2.4
Name: easytrajh5
Version: 0.2.17
Summary: MD trajectory library
Author-email: Bosco Ho <apposite@gmail.com>
License-File: LICENSE
Requires-Python: >=3.9
Requires-Dist: addict
Requires-Dist: appdirs
Requires-Dist: chevron
Requires-Dist: click
Requires-Dist: deepdiff
Requires-Dist: h5py
Requires-Dist: mdtraj
Requires-Dist: parmed==4.2.2
Requires-Dist: path
Requires-Dist: pydash
Requires-Dist: rich
Requires-Dist: ruyaml
